string_grouper/__init__.py
string_grouper/string_grouper.py
string_grouper/test/__init__.py
string_grouper/test/test_string_grouper.py
string_grouper-0.7.1.dist-info/LICENSE
string_grouper-0.7.1.dist-info/METADATA
string_grouper-0.7.1.dist-info/WHEEL
string_grouper-0.7.1.dist-info/RECORD
