Metadata-Version: 2.3
Name: string_grouper
Version: 0.7.1
Summary: String grouper contains functions to do string matching using TF-IDF and the cossine similarity.
License: MIT
Author: Chris van den Berg
Maintainer: Chris van den Berg
Requires-Python: >=3.9,<4.0
Classifier: License :: OSI Approved :: MIT License
Classifier: Programming Language :: Python :: 3
Classifier: Programming Language :: Python :: 3.9
Classifier: Programming Language :: Python :: 3.10
Classifier: Programming Language :: Python :: 3.11
Classifier: Programming Language :: Python :: 3.12
Classifier: Programming Language :: Python :: 3.13
Requires-Dist: loguru (>0.7.0)
Requires-Dist: numpy (>=1.26.0,<2.0.0)
Requires-Dist: pandas (>=2.0,<3.0)
Requires-Dist: scikit-learn (>=1.4.0,<2.0.0)
Requires-Dist: scipy (>=1.4.1)
Requires-Dist: sparse_dot_topn (>=1.1.0)
